jetblack_metrics/__init__.py
jetblack_metrics/metrics/__init__.py
jetblack_metrics/metrics/metric.py
jetblack_metrics/metrics/timed_metric.py
jetblack_metrics/monitor.py
jetblack_metrics/py.typed
jetblack_metrics-1.0.2.dist-info/LICENSE
jetblack_metrics-1.0.2.dist-info/WHEEL
jetblack_metrics-1.0.2.dist-info/METADATA
jetblack_metrics-1.0.2.dist-info/RECORD
