Metadata-Version: 2.1
Name: jetblack-metrics
Version: 1.0.2
Summary: Generic metrics and context bases monitoring
Home-page: https://github.com/rob-blackbourn/jetblack-metrics
License: Apache-2.0
Author: Rob Blackbourn
Author-email: rob.blackbourn@gmail.com
Requires-Python: >=3.7,<4.0
Classifier: License :: OSI Approved :: Apache Software License
Classifier: Programming Language :: Python :: 3
Classifier: Programming Language :: Python :: 3.7
Classifier: Programming Language :: Python :: 3.8
Classifier: Programming Language :: Python :: 3.9
Project-URL: Repository, https://github.com/rob-blackbourn/jetblack-metrics
